pyonfx/__init__.py
pyonfx/ass_core.py
pyonfx/convert.py
pyonfx/font_utility.py
pyonfx/shape.py
pyonfx/utils.py
pyonfx-0.10.1.dist-info/licenses/LICENSE
pyonfx-0.10.1.dist-info/METADATA
pyonfx-0.10.1.dist-info/WHEEL
pyonfx-0.10.1.dist-info/top_level.txt
pyonfx-0.10.1.dist-info/RECORD
