Metadata-Version: 2.4
Name: pyonfx
Version: 0.10.1
Summary: An easy way to create KFX (Karaoke Effects) and complex typesetting using the ASS format (Advanced Substation Alpha).
Author-email: Antonio Strippoli <clarantonio98@gmail.com>
License-Expression: LGPL-3.0-or-later
Project-URL: Documentation, https://pyonfx.rtfd.io/
Project-URL: Source, https://github.com/CoffeeStraw/PyonFX/
Project-URL: Tracker, https://github.com/CoffeeStraw/PyonFX/issues/
Keywords: typesetting,ass,subtitle,aegisub,karaoke,kfx,advanced-substation-alpha,karaoke-effect
Classifier: Development Status :: 4 - Beta
Classifier: Intended Audience :: Developers
Classifier: Programming Language :: Python
Classifier: Programming Language :: Python :: 3
Classifier: Programming Language :: Python :: 3.10
Classifier: Programming Language :: Python :: 3.11
Classifier: Programming Language :: Python :: 3.12
Classifier: Programming Language :: Python :: 3.13
Requires-Python: >=3.10
License-File: LICENSE
Requires-Dist: numpy
Requires-Dist: pyquaternion
Requires-Dist: shapely
Requires-Dist: scipy
Requires-Dist: VideoTimestamps>=0.2
Requires-Dist: pywin32; platform_system == "Windows"
Requires-Dist: pycairo; platform_system == "Linux" or platform_system == "Darwin"
Requires-Dist: PyGObject; platform_system == "Linux" or platform_system == "Darwin"
Provides-Extra: dev
Requires-Dist: black; extra == "dev"
Requires-Dist: pytest; extra == "dev"
Requires-Dist: pytest-check; extra == "dev"
Requires-Dist: sphinx>=5.0.0; extra == "dev"
Requires-Dist: sphinx_panels; extra == "dev"
Requires-Dist: sphinx_rtd_theme; extra == "dev"
Requires-Dist: sphinxcontrib-napoleon; extra == "dev"
Dynamic: license-file
